sncopy/__init__.py
sncopy/cli.py
sncopy/convert.py
sncopy-0.1.0.dist-info/entry_points.txt
sncopy-0.1.0.dist-info/LICENSE
sncopy-0.1.0.dist-info/WHEEL
sncopy-0.1.0.dist-info/METADATA
sncopy-0.1.0.dist-info/RECORD
