Metadata-Version: 2.1
Name: sncopy
Version: 0.1.0
Summary: Copy-Paste Tool from Slack to Notion
Home-page: https://github.com/kenichihiguchi/sncopy
License: Apache-2.0
Author: Kenichi Higuchi
Author-email: higuchi@adansons.co.jp
Requires-Python: >=3.8,<4.0
Classifier: License :: OSI Approved :: Apache Software License
Classifier: Programming Language :: Python :: 3
Classifier: Programming Language :: Python :: 3.10
Classifier: Programming Language :: Python :: 3.8
Classifier: Programming Language :: Python :: 3.9
Requires-Dist: click (>=8.1.3,<9.0.0)
Requires-Dist: pyperclip (>=1.8.2,<2.0.0)
Project-URL: Repository, https://github.com/kenichihiguchi/sncopy
